{"id": "gen9randombattle-2540490269", "format": "[Gen 9] Random Battle", "players": ["RustySheriffBadge", "Mrs dad"], "log": "|j|☆RustySheriffBadge\n|j|☆Mrs dad\n|t:|1771208520\n|gametype|singles\n|player|p1|RustySheriffBadge|#rsb|1941\n|player|p2|Mrs dad|veteran-gen4|1956\n|gen|9\n|tier|[Gen 9] Random Battle\n|rated|\n|rule|Species Clause: Limit one of each Pokémon\n|rule|HP Percentage Mod: HP is shown in percentages\n|rule|Sleep Clause Mod: Limit one foe put to sleep\n|rule|Illusion Level Mod: Illusion disguises the Pokémon's true level\n|\n|t:|1771208520\n|teamsize|p1|6\n|teamsize|p2|6\n|start\n|switch|p1a: Vivillon|Vivillon-Jungle, L83, M|268/268\n|switch|p2a: Rampardos|Rampardos, L90, F|321/321\n|turn|1\n|inactive|Battle timer is ON: inactive players will automatically lose when time's up. (requested by Mrs dad)\n|inactive|Mrs dad has 120 seconds left.\n|j| ugly ahh dumpling\n|\n|t:|1771208560\n|switch|p1a: Hippowdon|Hippowdon, L82, M|311/311\n|-weather|Sandstorm|[from] ability: Sand Stream|[of] p1a: Hippowdon\n|move|p2a: Rampardos|Fire Punch|p1a: Hippowdon\n|-damage|p1a: Hippowdon|173/311\n|\n|-weather|Sandstorm|[upkeep]\n|-heal|p1a: Hippowdon|192/311|[from] item: Leftovers\n|upkeep\n|turn|2\n|\n|t:|1771208573\n|switch|p2a: Landorus|Landorus-Therian, L76, M|260/260\n|-ability|p2a: Landorus|Intimidate|boost\n|-unboost|p1a: Hippowdon|atk|1\n|move|p1a: Hippowdon|Slack Off|p1a: Hippowdon\n|-heal|p1a: Hippowdon|311/311\n|\n|-weather|Sandstorm|[upkeep]\n|upkeep\n|turn|3\n|\n|t:|1771208577\n|move|p2a: Landorus|Taunt|p1a: Hippowdon\n|-start|p1a: Hippowdon|move: Taunt\n|move|p1a: Hippowdon|Stone Edge|p2a: Landorus|[miss]\n|-miss|p1a: Hippowdon|p2a: Landorus\n|\n|-weather|Sandstorm|[upkeep]\n|upkeep\n|turn|4\n|-message|RustySheriffBadge forfeited.\n|\n|win|Mrs dad\n|raw|RustySheriffBadge's rating: 1941 &rarr; <strong>1922</strong><br />(-19 for losing)\n|raw|Mrs dad's rating: 1956 &rarr; <strong>1975</strong><br />(+19 for winning)\n|l|☆RustySheriffBadge\n|player|p1|\n|l|☆Mrs dad\n|player|p2|\n|j|☆Mrs dad\n|player|p2|Mrs dad|veteran-gen4|\n", "inputlog": ">version 686819e5e19f8a7fd2345cfc5a08a5085efa2cc3\n>start {\"formatid\":\"gen9randombattle\",\"seed\":\"sodium,6209b8a3349aefcd7f0c83744d895678\",\"rated\":\"Rated battle\"}\n>player p1 {\"name\":\"RustySheriffBadge\",\"avatar\":\"#rsb\",\"rating\":1941,\"seed\":\"sodium,98c50fc5d9120009a464447326fe9586\"}\n>player p2 {\"name\":\"Mrs dad\",\"avatar\":\"veteran-gen4\",\"rating\":1956,\"seed\":\"sodium,ecd2708a8d9bcc7fec1a786f29733984\"}\n>p1 switch 6\n>p2 move firepunch\n>p1 move slackoff\n>p2 switch 2\n>p1 move stoneedge\n>p2 move taunt\n>forcelose p1", "uploadtime": 1771208593, "views": 11, "formatid": "gen9randombattle", "rating": 1922, "private": 0, "password": null}