{"nodes": [{"id": "pokemon_showdown_server_modlog_index_ts", "label": "index.ts", "file_type": "code", "source_file": "Pokemon Showdown/server/modlog/index.ts", "source_location": "L1"}, {"id": "index_modlog", "label": "Modlog", "file_type": "code", "source_file": "Pokemon Showdown/server/modlog/index.ts", "source_location": "L85"}, {"id": "index_modlog_constructor", "label": ".constructor()", "file_type": "code", "source_file": "Pokemon Showdown/server/modlog/index.ts", "source_location": "L97"}, {"id": "index_modlog_setupdatabase", "label": ".setupDatabase()", "file_type": "code", "source_file": "Pokemon Showdown/server/modlog/index.ts", "source_location": "L139"}, {"id": "index_modlog_getsharedid", "label": ".getSharedID()", "file_type": "code", "source_file": "Pokemon Showdown/server/modlog/index.ts", "source_location": "L181"}, {"id": "index_modlog_initialize", "label": ".initialize()", "file_type": "code", "source_file": "Pokemon Showdown/server/modlog/index.ts", "source_location": "L190"}, {"id": "index_modlog_write", "label": ".write()", "file_type": "code", "source_file": "Pokemon Showdown/server/modlog/index.ts", "source_location": "L195"}, {"id": "index_modlog_writesql", "label": ".writeSQL()", "file_type": "code", "source_file": "Pokemon Showdown/server/modlog/index.ts", "source_location": "L215"}, {"id": "index_modlog_destroy", "label": ".destroy()", "file_type": "code", "source_file": "Pokemon Showdown/server/modlog/index.ts", "source_location": "L232"}, {"id": "index_modlog_destroyallsqlite", "label": ".destroyAllSQLite()", "file_type": "code", "source_file": "Pokemon Showdown/server/modlog/index.ts", "source_location": "L236"}, {"id": "index_modlog_destroyall", "label": ".destroyAll()", "file_type": "code", "source_file": "Pokemon Showdown/server/modlog/index.ts", "source_location": "L242"}, {"id": "index_modlog_rename", "label": ".rename()", "file_type": "code", "source_file": "Pokemon Showdown/server/modlog/index.ts", "source_location": "L246"}, {"id": "index_modlog_getglobalpunishments", "label": ".getGlobalPunishments()", "file_type": "code", "source_file": "Pokemon Showdown/server/modlog/index.ts", "source_location": "L264"}, {"id": "index_modlog_getglobalpunishmentssql", "label": ".getGlobalPunishmentsSQL()", "file_type": "code", "source_file": "Pokemon Showdown/server/modlog/index.ts", "source_location": "L269"}, {"id": "index_modlog_search", "label": ".search()", "file_type": "code", "source_file": "Pokemon Showdown/server/modlog/index.ts", "source_location": "L287"}, {"id": "index_modlog_dbrowtomodlogentry", "label": ".dbRowToModlogEntry()", "file_type": "code", "source_file": "Pokemon Showdown/server/modlog/index.ts", "source_location": "L320"}, {"id": "index_modlog_buildparallelindexscanquery", "label": ".buildParallelIndexScanQuery()", "file_type": "code", "source_file": "Pokemon Showdown/server/modlog/index.ts", "source_location": "L347"}, {"id": "index_modlog_preparesqlsearch", "label": ".prepareSQLSearch()", "file_type": "code", "source_file": "Pokemon Showdown/server/modlog/index.ts", "source_location": "L385"}], "edges": [{"source": "pokemon_showdown_server_modlog_index_ts", "target": "pokemon_showdown_server_modlog_lib", "relation": "imports_from", "confidence": "EXTRACTED", "source_file": "Pokemon Showdown/server/modlog/index.ts", "source_location": "L11", "weight": 1.0}, {"source": "pokemon_showdown_server_modlog_index_ts", "target": "pokemon_showdown_server_modlog_config_loader", "relation": "imports_from", "confidence": "EXTRACTED", "source_file": "Pokemon Showdown/server/modlog/index.ts", "source_location": "L12", "weight": 1.0}, {"source": "pokemon_showdown_server_modlog_index_ts", "target": "index_modlog", "relation": "contains", "confidence": "EXTRACTED", "source_file": "Pokemon Showdown/server/modlog/index.ts", "source_location": "L85", "weight": 1.0}, {"source": "index_modlog", "target": "index_modlog_constructor", "relation": "method", "confidence": "EXTRACTED", "source_file": "Pokemon Showdown/server/modlog/index.ts", "source_location": "L97", "weight": 1.0}, {"source": "index_modlog", "target": "index_modlog_setupdatabase", "relation": "method", "confidence": "EXTRACTED", "source_file": "Pokemon Showdown/server/modlog/index.ts", "source_location": "L139", "weight": 1.0}, {"source": "index_modlog", "target": "index_modlog_getsharedid", "relation": "method", "confidence": "EXTRACTED", "source_file": "Pokemon Showdown/server/modlog/index.ts", "source_location": "L181", "weight": 1.0}, {"source": "index_modlog", "target": "index_modlog_initialize", "relation": "method", "confidence": "EXTRACTED", "source_file": "Pokemon Showdown/server/modlog/index.ts", "source_location": "L190", "weight": 1.0}, {"source": "index_modlog", "target": "index_modlog_write", "relation": "method", "confidence": "EXTRACTED", "source_file": "Pokemon Showdown/server/modlog/index.ts", "source_location": "L195", "weight": 1.0}, {"source": "index_modlog", "target": "index_modlog_writesql", "relation": "method", "confidence": "EXTRACTED", "source_file": "Pokemon Showdown/server/modlog/index.ts", "source_location": "L215", "weight": 1.0}, {"source": "index_modlog", "target": "index_modlog_destroy", "relation": "method", "confidence": "EXTRACTED", "source_file": "Pokemon Showdown/server/modlog/index.ts", "source_location": "L232", "weight": 1.0}, {"source": "index_modlog", "target": "index_modlog_destroyallsqlite", "relation": "method", "confidence": "EXTRACTED", "source_file": "Pokemon Showdown/server/modlog/index.ts", "source_location": "L236", "weight": 1.0}, {"source": "index_modlog", "target": "index_modlog_destroyall", "relation": "method", "confidence": "EXTRACTED", "source_file": "Pokemon Showdown/server/modlog/index.ts", "source_location": "L242", "weight": 1.0}, {"source": "index_modlog", "target": "index_modlog_rename", "relation": "method", "confidence": "EXTRACTED", "source_file": "Pokemon Showdown/server/modlog/index.ts", "source_location": "L246", "weight": 1.0}, {"source": "index_modlog", "target": "index_modlog_getglobalpunishments", "relation": "method", "confidence": "EXTRACTED", "source_file": "Pokemon Showdown/server/modlog/index.ts", "source_location": "L264", "weight": 1.0}, {"source": "index_modlog", "target": "index_modlog_getglobalpunishmentssql", "relation": "method", "confidence": "EXTRACTED", "source_file": "Pokemon Showdown/server/modlog/index.ts", "source_location": "L269", "weight": 1.0}, {"source": "index_modlog", "target": "index_modlog_search", "relation": "method", "confidence": "EXTRACTED", "source_file": "Pokemon Showdown/server/modlog/index.ts", "source_location": "L287", "weight": 1.0}, {"source": "index_modlog", "target": "index_modlog_dbrowtomodlogentry", "relation": "method", "confidence": "EXTRACTED", "source_file": "Pokemon Showdown/server/modlog/index.ts", "source_location": "L320", "weight": 1.0}, {"source": "index_modlog", "target": "index_modlog_buildparallelindexscanquery", "relation": "method", "confidence": "EXTRACTED", "source_file": "Pokemon Showdown/server/modlog/index.ts", "source_location": "L347", "weight": 1.0}, {"source": "index_modlog", "target": "index_modlog_preparesqlsearch", "relation": "method", "confidence": "EXTRACTED", "source_file": "Pokemon Showdown/server/modlog/index.ts", "source_location": "L385", "weight": 1.0}, {"source": "index_modlog_constructor", "target": "index_modlog_setupdatabase", "relation": "calls", "confidence": "EXTRACTED", "source_file": "Pokemon Showdown/server/modlog/index.ts", "source_location": "L133", "weight": 1.0}, {"source": "index_modlog_setupdatabase", "target": "index_modlog_writesql", "relation": "calls", "confidence": "EXTRACTED", "source_file": "Pokemon Showdown/server/modlog/index.ts", "source_location": "L174", "weight": 1.0}, {"source": "index_modlog_write", "target": "index_modlog_writesql", "relation": "calls", "confidence": "EXTRACTED", "source_file": "Pokemon Showdown/server/modlog/index.ts", "source_location": "L212", "weight": 1.0}, {"source": "index_modlog_destroyallsqlite", "target": "index_modlog_destroy", "relation": "calls", "confidence": "EXTRACTED", "source_file": "Pokemon Showdown/server/modlog/index.ts", "source_location": "L238", "weight": 1.0}, {"source": "index_modlog_destroyall", "target": "index_modlog_destroyallsqlite", "relation": "calls", "confidence": "EXTRACTED", "source_file": "Pokemon Showdown/server/modlog/index.ts", "source_location": "L243", "weight": 1.0}, {"source": "index_modlog_getglobalpunishments", "target": "index_modlog_getglobalpunishmentssql", "relation": "calls", "confidence": "EXTRACTED", "source_file": "Pokemon Showdown/server/modlog/index.ts", "source_location": "L266", "weight": 1.0}, {"source": "index_modlog_search", "target": "index_modlog_preparesqlsearch", "relation": "calls", "confidence": "EXTRACTED", "source_file": "Pokemon Showdown/server/modlog/index.ts", "source_location": "L309", "weight": 1.0}, {"source": "index_modlog_preparesqlsearch", "target": "index_modlog_buildparallelindexscanquery", "relation": "calls", "confidence": "EXTRACTED", "source_file": "Pokemon Showdown/server/modlog/index.ts", "source_location": "L474", "weight": 1.0}], "raw_calls": [{"caller_nid": "index_modlog_constructor", "callee": "SQL", "source_file": "Pokemon Showdown/server/modlog/index.ts", "source_location": "L108"}, {"caller_nid": "index_modlog_constructor", "callee": "spawn", "source_file": "Pokemon Showdown/server/modlog/index.ts", "source_location": "L116"}, {"caller_nid": "index_modlog_constructor", "callee": "on", "source_file": "Pokemon Showdown/server/modlog/index.ts", "source_location": "L124"}, {"caller_nid": "index_modlog_constructor", "callee": "on", "source_file": "Pokemon Showdown/server/modlog/index.ts", "source_location": "L127"}, {"caller_nid": "index_modlog_constructor", "callee": "then", "source_file": "Pokemon Showdown/server/modlog/index.ts", "source_location": "L133"}, {"caller_nid": "index_modlog_setupdatabase", "callee": "exec", "source_file": "Pokemon Showdown/server/modlog/index.ts", "source_location": "L141"}, {"caller_nid": "index_modlog_setupdatabase", "callee": "exec", "source_file": "Pokemon Showdown/server/modlog/index.ts", "source_location": "L142"}, {"caller_nid": "index_modlog_setupdatabase", "callee": "get", "source_file": "Pokemon Showdown/server/modlog/index.ts", "source_location": "L145"}, {"caller_nid": "index_modlog_setupdatabase", "callee": "runFile", "source_file": "Pokemon Showdown/server/modlog/index.ts", "source_location": "L147"}, {"caller_nid": "index_modlog_setupdatabase", "callee": "get", "source_file": "Pokemon Showdown/server/modlog/index.ts", "source_location": "L150"}, {"caller_nid": "index_modlog_setupdatabase", "callee": "warnFunction", "source_file": "Pokemon Showdown/server/modlog/index.ts", "source_location": "L157"}, {"caller_nid": "index_modlog_setupdatabase", "callee": "runFile", "source_file": "Pokemon Showdown/server/modlog/index.ts", "source_location": "L158"}, {"caller_nid": "index_modlog_setupdatabase", "callee": "warnFunction", "source_file": "Pokemon Showdown/server/modlog/index.ts", "source_location": "L159"}, {"caller_nid": "index_modlog_setupdatabase", "callee": "prepare", "source_file": "Pokemon Showdown/server/modlog/index.ts", "source_location": "L162"}, {"caller_nid": "index_modlog_setupdatabase", "callee": "prepare", "source_file": "Pokemon Showdown/server/modlog/index.ts", "source_location": "L166"}, {"caller_nid": "index_modlog_setupdatabase", "callee": "prepare", "source_file": "Pokemon Showdown/server/modlog/index.ts", "source_location": "L167"}, {"caller_nid": "index_modlog_setupdatabase", "callee": "prepare", "source_file": "Pokemon Showdown/server/modlog/index.ts", "source_location": "L168"}, {"caller_nid": "index_modlog_setupdatabase", "callee": "formatSQLArray", "source_file": "Pokemon Showdown/server/modlog/index.ts", "source_location": "L172"}, {"caller_nid": "index_modlog_getsharedid", "callee": "includes", "source_file": "Pokemon Showdown/server/modlog/index.ts", "source_location": "L182"}, {"caller_nid": "index_modlog_getsharedid", "callee": "toID", "source_file": "Pokemon Showdown/server/modlog/index.ts", "source_location": "L182"}, {"caller_nid": "index_modlog_getsharedid", "callee": "split", "source_file": "Pokemon Showdown/server/modlog/index.ts", "source_location": "L182"}, {"caller_nid": "index_modlog_write", "callee": "now", "source_file": "Pokemon Showdown/server/modlog/index.ts", "source_location": "L209"}, {"caller_nid": "index_modlog_writesql", "callee": "push", "source_file": "Pokemon Showdown/server/modlog/index.ts", "source_location": "L218"}, {"caller_nid": "index_modlog_writesql", "callee": "toString", "source_file": "Pokemon Showdown/server/modlog/index.ts", "source_location": "L223"}, {"caller_nid": "index_modlog_writesql", "callee": "toString", "source_file": "Pokemon Showdown/server/modlog/index.ts", "source_location": "L224"}, {"caller_nid": "index_modlog_writesql", "callee": "transaction", "source_file": "Pokemon Showdown/server/modlog/index.ts", "source_location": "L226"}, {"caller_nid": "index_modlog_destroy", "callee": "resolve", "source_file": "Pokemon Showdown/server/modlog/index.ts", "source_location": "L233"}, {"caller_nid": "index_modlog_rename", "callee": "run", "source_file": "Pokemon Showdown/server/modlog/index.ts", "source_location": "L253"}, {"caller_nid": "index_modlog_getglobalpunishments", "callee": "toID", "source_file": "Pokemon Showdown/server/modlog/index.ts", "source_location": "L266"}, {"caller_nid": "index_modlog_getglobalpunishmentssql", "callee": "now", "source_file": "Pokemon Showdown/server/modlog/index.ts", "source_location": "L276"}, {"caller_nid": "index_modlog_getglobalpunishmentssql", "callee": "all", "source_file": "Pokemon Showdown/server/modlog/index.ts", "source_location": "L278"}, {"caller_nid": "index_modlog_search", "callee": "now", "source_file": "Pokemon Showdown/server/modlog/index.ts", "source_location": "L294"}, {"caller_nid": "index_modlog_search", "callee": "map", "source_file": "Pokemon Showdown/server/modlog/index.ts", "source_location": "L298"}, {"caller_nid": "index_modlog_search", "callee": "filter", "source_file": "Pokemon Showdown/server/modlog/index.ts", "source_location": "L298"}, {"caller_nid": "index_modlog_search", "callee": "values", "source_file": "Pokemon Showdown/server/modlog/index.ts", "source_location": "L298"}, {"caller_nid": "index_modlog_search", "callee": "map", "source_file": "Pokemon Showdown/server/modlog/index.ts", "source_location": "L310"}, {"caller_nid": "index_modlog_search", "callee": "all", "source_file": "Pokemon Showdown/server/modlog/index.ts", "source_location": "L310"}, {"caller_nid": "index_modlog_search", "callee": "now", "source_file": "Pokemon Showdown/server/modlog/index.ts", "source_location": "L313"}, {"caller_nid": "index_modlog_search", "callee": "slow", "source_file": "Pokemon Showdown/server/modlog/index.ts", "source_location": "L315"}, {"caller_nid": "index_modlog_search", "callee": "stringify", "source_file": "Pokemon Showdown/server/modlog/index.ts", "source_location": "L315"}, {"caller_nid": "index_modlog_dbrowtomodlogentry", "callee": "split", "source_file": "Pokemon Showdown/server/modlog/index.ts", "source_location": "L328"}, {"caller_nid": "index_modlog_dbrowtomodlogentry", "callee": "Boolean", "source_file": "Pokemon Showdown/server/modlog/index.ts", "source_location": "L330"}, {"caller_nid": "index_modlog_buildparallelindexscanquery", "callee": "push", "source_file": "Pokemon Showdown/server/modlog/index.ts", "source_location": "L360"}, {"caller_nid": "index_modlog_buildparallelindexscanquery", "callee": "push", "source_file": "Pokemon Showdown/server/modlog/index.ts", "source_location": "L368"}, {"caller_nid": "index_modlog_buildparallelindexscanquery", "callee": "push", "source_file": "Pokemon Showdown/server/modlog/index.ts", "source_location": "L373"}, {"caller_nid": "index_modlog_buildparallelindexscanquery", "callee": "push", "source_file": "Pokemon Showdown/server/modlog/index.ts", "source_location": "L377"}, {"caller_nid": "index_modlog_preparesqlsearch", "callee": "push", "source_file": "Pokemon Showdown/server/modlog/index.ts", "source_location": "L397"}, {"caller_nid": "index_modlog_preparesqlsearch", "callee": "formatSQLArray", "source_file": "Pokemon Showdown/server/modlog/index.ts", "source_location": "L404"}, {"caller_nid": "index_modlog_preparesqlsearch", "callee": "includes", "source_file": "Pokemon Showdown/server/modlog/index.ts", "source_location": "L405"}, {"caller_nid": "index_modlog_preparesqlsearch", "callee": "pop", "source_file": "Pokemon Showdown/server/modlog/index.ts", "source_location": "L411"}, {"caller_nid": "index_modlog_preparesqlsearch", "callee": "push", "source_file": "Pokemon Showdown/server/modlog/index.ts", "source_location": "L414"}, {"caller_nid": "index_modlog_preparesqlsearch", "callee": "push", "source_file": "Pokemon Showdown/server/modlog/index.ts", "source_location": "L420"}, {"caller_nid": "index_modlog_preparesqlsearch", "callee": "push", "source_file": "Pokemon Showdown/server/modlog/index.ts", "source_location": "L422"}, {"caller_nid": "index_modlog_preparesqlsearch", "callee": "push", "source_file": "Pokemon Showdown/server/modlog/index.ts", "source_location": "L427"}, {"caller_nid": "index_modlog_preparesqlsearch", "callee": "formatSQLArray", "source_file": "Pokemon Showdown/server/modlog/index.ts", "source_location": "L427"}, {"caller_nid": "index_modlog_preparesqlsearch", "callee": "push", "source_file": "Pokemon Showdown/server/modlog/index.ts", "source_location": "L433"}, {"caller_nid": "index_modlog_preparesqlsearch", "callee": "push", "source_file": "Pokemon Showdown/server/modlog/index.ts", "source_location": "L435"}, {"caller_nid": "index_modlog_preparesqlsearch", "callee": "push", "source_file": "Pokemon Showdown/server/modlog/index.ts", "source_location": "L441"}, {"caller_nid": "index_modlog_preparesqlsearch", "callee": "push", "source_file": "Pokemon Showdown/server/modlog/index.ts", "source_location": "L443"}, {"caller_nid": "index_modlog_preparesqlsearch", "callee": "push", "source_file": "Pokemon Showdown/server/modlog/index.ts", "source_location": "L451"}, {"caller_nid": "index_modlog_preparesqlsearch", "callee": "push", "source_file": "Pokemon Showdown/server/modlog/index.ts", "source_location": "L453"}, {"caller_nid": "index_modlog_preparesqlsearch", "callee": "toLowerCase", "source_file": "Pokemon Showdown/server/modlog/index.ts", "source_location": "L462"}, {"caller_nid": "index_modlog_preparesqlsearch", "callee": "toLowerCase", "source_file": "Pokemon Showdown/server/modlog/index.ts", "source_location": "L465"}, {"caller_nid": "index_modlog_preparesqlsearch", "callee": "push", "source_file": "Pokemon Showdown/server/modlog/index.ts", "source_location": "L468"}, {"caller_nid": "index_modlog_preparesqlsearch", "callee": "push", "source_file": "Pokemon Showdown/server/modlog/index.ts", "source_location": "L469"}]}