{"nodes": [{"id": "pokemon_showdown_server_index_ts", "label": "index.ts", "file_type": "code", "source_file": "Pokemon Showdown/server/index.ts", "source_location": "L1"}, {"id": "index_setupglobals", "label": "setupGlobals()", "file_type": "code", "source_file": "Pokemon Showdown/server/index.ts", "source_location": "L64"}, {"id": "index_listen", "label": "listen()", "file_type": "code", "source_file": "Pokemon Showdown/server/index.ts", "source_location": "L148"}], "edges": [{"source": "pokemon_showdown_server_index_ts", "target": "pokemon_showdown_server_lib", "relation": "imports_from", "confidence": "EXTRACTED", "source_file": "Pokemon Showdown/server/index.ts", "source_location": "L57", "weight": 1.0}, {"source": "pokemon_showdown_server_index_ts", "target": "index_setupglobals", "relation": "contains", "confidence": "EXTRACTED", "source_file": "Pokemon Showdown/server/index.ts", "source_location": "L64", "weight": 1.0}, {"source": "pokemon_showdown_server_index_ts", "target": "pokemon_showdown_server_sockets", "relation": "imports_from", "confidence": "EXTRACTED", "source_file": "Pokemon Showdown/server/index.ts", "source_location": "L145", "weight": 1.0}, {"source": "pokemon_showdown_server_index_ts", "target": "index_listen", "relation": "contains", "confidence": "EXTRACTED", "source_file": "Pokemon Showdown/server/index.ts", "source_location": "L148", "weight": 1.0}, {"source": "pokemon_showdown_server_index_ts", "target": "pokemon_showdown_server_team_validator_async", "relation": "imports_from", "confidence": "EXTRACTED", "source_file": "Pokemon Showdown/server/index.ts", "source_location": "L170", "weight": 1.0}], "raw_calls": [{"caller_nid": "index_setupglobals", "callee": "require", "source_file": "Pokemon Showdown/server/index.ts", "source_location": "L65"}, {"caller_nid": "index_setupglobals", "callee": "require", "source_file": "Pokemon Showdown/server/index.ts", "source_location": "L68"}, {"caller_nid": "index_setupglobals", "callee": "then", "source_file": "Pokemon Showdown/server/index.ts", "source_location": "L71"}, {"caller_nid": "index_setupglobals", "callee": "version", "source_file": "Pokemon Showdown/server/index.ts", "source_location": "L71"}, {"caller_nid": "index_setupglobals", "callee": "cleanup", "source_file": "Pokemon Showdown/server/index.ts", "source_location": "L74"}, {"caller_nid": "index_setupglobals", "callee": "onModify", "source_file": "Pokemon Showdown/server/index.ts", "source_location": "L77"}, {"caller_nid": "index_setupglobals", "callee": "FS", "source_file": "Pokemon Showdown/server/index.ts", "source_location": "L77"}, {"caller_nid": "index_setupglobals", "callee": "require", "source_file": "Pokemon Showdown/server/index.ts", "source_location": "L90"}, {"caller_nid": "index_setupglobals", "callee": "require", "source_file": "Pokemon Showdown/server/index.ts", "source_location": "L94"}, {"caller_nid": "index_setupglobals", "callee": "require", "source_file": "Pokemon Showdown/server/index.ts", "source_location": "L97"}, {"caller_nid": "index_setupglobals", "callee": "require", "source_file": "Pokemon Showdown/server/index.ts", "source_location": "L100"}, {"caller_nid": "index_setupglobals", "callee": "require", "source_file": "Pokemon Showdown/server/index.ts", "source_location": "L103"}, {"caller_nid": "index_setupglobals", "callee": "require", "source_file": "Pokemon Showdown/server/index.ts", "source_location": "L106"}, {"caller_nid": "index_setupglobals", "callee": "require", "source_file": "Pokemon Showdown/server/index.ts", "source_location": "L109"}, {"caller_nid": "index_setupglobals", "callee": "require", "source_file": "Pokemon Showdown/server/index.ts", "source_location": "L112"}, {"caller_nid": "index_setupglobals", "callee": "require", "source_file": "Pokemon Showdown/server/index.ts", "source_location": "L117"}, {"caller_nid": "index_setupglobals", "callee": "spawn", "source_file": "Pokemon Showdown/server/index.ts", "source_location": "L119"}, {"caller_nid": "index_setupglobals", "callee": "require", "source_file": "Pokemon Showdown/server/index.ts", "source_location": "L121"}, {"caller_nid": "index_setupglobals", "callee": "require", "source_file": "Pokemon Showdown/server/index.ts", "source_location": "L124"}, {"caller_nid": "index_setupglobals", "callee": "loadHostsAndRanges", "source_file": "Pokemon Showdown/server/index.ts", "source_location": "L126"}]}