{"nodes": [{"id": "pokemon_showdown_pokemon_showdown_0_11_10_server_chat_plugins_hosts_ts", "label": "hosts.ts", "file_type": "code", "source_file": "Pokemon Showdown/pokemon-showdown-0.11.10/server/chat-plugins/hosts.ts", "source_location": "L1"}, {"id": "hosts_checkcanperform", "label": "checkCanPerform()", "file_type": "code", "source_file": "Pokemon Showdown/pokemon-showdown-0.11.10/server/chat-plugins/hosts.ts", "source_location": "L17"}, {"id": "hosts_gethosttype", "label": "getHostType()", "file_type": "code", "source_file": "Pokemon Showdown/pokemon-showdown-0.11.10/server/chat-plugins/hosts.ts", "source_location": "L23"}, {"id": "hosts_visualizerangelist", "label": "visualizeRangeList()", "file_type": "code", "source_file": "Pokemon Showdown/pokemon-showdown-0.11.10/server/chat-plugins/hosts.ts", "source_location": "L30"}, {"id": "hosts_formatrange", "label": "formatRange()", "file_type": "code", "source_file": "Pokemon Showdown/pokemon-showdown-0.11.10/server/chat-plugins/hosts.ts", "source_location": "L42"}], "edges": [{"source": "pokemon_showdown_pokemon_showdown_0_11_10_server_chat_plugins_hosts_ts", "target": "pokemon_showdown_pokemon_showdown_0_11_10_server_chat_plugins_lib", "relation": "imports_from", "confidence": "EXTRACTED", "source_file": "Pokemon Showdown/pokemon-showdown-0.11.10/server/chat-plugins/hosts.ts", "source_location": "L7", "weight": 1.0}, {"source": "pokemon_showdown_pokemon_showdown_0_11_10_server_chat_plugins_hosts_ts", "target": "pokemon_showdown_pokemon_showdown_0_11_10_server_chat_plugins_ip_tools", "relation": "imports_from", "confidence": "EXTRACTED", "source_file": "Pokemon Showdown/pokemon-showdown-0.11.10/server/chat-plugins/hosts.ts", "source_location": "L8", "weight": 1.0}, {"source": "pokemon_showdown_pokemon_showdown_0_11_10_server_chat_plugins_hosts_ts", "target": "pokemon_showdown_pokemon_showdown_0_11_10_server_chat_plugins_user_groups", "relation": "imports_from", "confidence": "EXTRACTED", "source_file": "Pokemon Showdown/pokemon-showdown-0.11.10/server/chat-plugins/hosts.ts", "source_location": "L9", "weight": 1.0}, {"source": "pokemon_showdown_pokemon_showdown_0_11_10_server_chat_plugins_hosts_ts", "target": "hosts_checkcanperform", "relation": "contains", "confidence": "EXTRACTED", "source_file": "Pokemon Showdown/pokemon-showdown-0.11.10/server/chat-plugins/hosts.ts", "source_location": "L17", "weight": 1.0}, {"source": "pokemon_showdown_pokemon_showdown_0_11_10_server_chat_plugins_hosts_ts", "target": "hosts_gethosttype", "relation": "contains", "confidence": "EXTRACTED", "source_file": "Pokemon Showdown/pokemon-showdown-0.11.10/server/chat-plugins/hosts.ts", "source_location": "L23", "weight": 1.0}, {"source": "pokemon_showdown_pokemon_showdown_0_11_10_server_chat_plugins_hosts_ts", "target": "hosts_visualizerangelist", "relation": "contains", "confidence": "EXTRACTED", "source_file": "Pokemon Showdown/pokemon-showdown-0.11.10/server/chat-plugins/hosts.ts", "source_location": "L30", "weight": 1.0}, {"source": "pokemon_showdown_pokemon_showdown_0_11_10_server_chat_plugins_hosts_ts", "target": "hosts_formatrange", "relation": "contains", "confidence": "EXTRACTED", "source_file": "Pokemon Showdown/pokemon-showdown-0.11.10/server/chat-plugins/hosts.ts", "source_location": "L42", "weight": 1.0}], "raw_calls": [{"caller_nid": "hosts_checkcanperform", "callee": "includes", "source_file": "Pokemon Showdown/pokemon-showdown-0.11.10/server/chat-plugins/hosts.ts", "source_location": "L20"}, {"caller_nid": "hosts_checkcanperform", "callee": "checkCan", "source_file": "Pokemon Showdown/pokemon-showdown-0.11.10/server/chat-plugins/hosts.ts", "source_location": "L20"}, {"caller_nid": "hosts_gethosttype", "callee": "toID", "source_file": "Pokemon Showdown/pokemon-showdown-0.11.10/server/chat-plugins/hosts.ts", "source_location": "L24"}, {"caller_nid": "hosts_gethosttype", "callee": "includes", "source_file": "Pokemon Showdown/pokemon-showdown-0.11.10/server/chat-plugins/hosts.ts", "source_location": "L25"}, {"caller_nid": "hosts_gethosttype", "callee": "join", "source_file": "Pokemon Showdown/pokemon-showdown-0.11.10/server/chat-plugins/hosts.ts", "source_location": "L27"}, {"caller_nid": "hosts_visualizerangelist", "callee": "numberToIP", "source_file": "Pokemon Showdown/pokemon-showdown-0.11.10/server/chat-plugins/hosts.ts", "source_location": "L34"}, {"caller_nid": "hosts_visualizerangelist", "callee": "numberToIP", "source_file": "Pokemon Showdown/pokemon-showdown-0.11.10/server/chat-plugins/hosts.ts", "source_location": "L35"}, {"caller_nid": "hosts_visualizerangelist", "callee": "html", "source_file": "Pokemon Showdown/pokemon-showdown-0.11.10/server/chat-plugins/hosts.ts", "source_location": "L36"}, {"caller_nid": "hosts_formatrange", "callee": "numberToIP", "source_file": "Pokemon Showdown/pokemon-showdown-0.11.10/server/chat-plugins/hosts.ts", "source_location": "L46"}, {"caller_nid": "hosts_formatrange", "callee": "numberToIP", "source_file": "Pokemon Showdown/pokemon-showdown-0.11.10/server/chat-plugins/hosts.ts", "source_location": "L47"}]}