{"nodes": [{"id": "fixes_scripts_sync_commands_py", "label": "scripts__sync_commands.py", "file_type": "code", "source_file": "fixes/scripts__sync_commands.py", "source_location": "L1"}, {"id": "scripts_sync_commands_main", "label": "main()", "file_type": "code", "source_file": "fixes/scripts__sync_commands.py", "source_location": "L22"}, {"id": "scripts_sync_commands_rationale_1", "label": "One-shot command sync script. Loads all cogs, syncs slash commands to the config", "file_type": "rationale", "source_file": "fixes/scripts__sync_commands.py", "source_location": "L1"}], "edges": [{"source": "fixes_scripts_sync_commands_py", "target": "asyncio", "relation": "imports", "confidence": "EXTRACTED", "source_file": "fixes/scripts__sync_commands.py", "source_location": "L8", "weight": 1.0}, {"source": "fixes_scripts_sync_commands_py", "target": "sys", "relation": "imports", "confidence": "EXTRACTED", "source_file": "fixes/scripts__sync_commands.py", "source_location": "L9", "weight": 1.0}, {"source": "fixes_scripts_sync_commands_py", "target": "pathlib", "relation": "imports_from", "confidence": "EXTRACTED", "source_file": "fixes/scripts__sync_commands.py", "source_location": "L10", "weight": 1.0}, {"source": "fixes_scripts_sync_commands_py", "target": "discord", "relation": "imports", "confidence": "EXTRACTED", "source_file": "fixes/scripts__sync_commands.py", "source_location": "L14", "weight": 1.0}, {"source": "fixes_scripts_sync_commands_py", "target": "discord_ext", "relation": "imports_from", "confidence": "EXTRACTED", "source_file": "fixes/scripts__sync_commands.py", "source_location": "L15", "weight": 1.0}, {"source": "fixes_scripts_sync_commands_py", "target": "src_config", "relation": "imports_from", "confidence": "EXTRACTED", "source_file": "fixes/scripts__sync_commands.py", "source_location": "L16", "weight": 1.0}, {"source": "fixes_scripts_sync_commands_py", "target": "src_bot_main", "relation": "imports_from", "confidence": "EXTRACTED", "source_file": "fixes/scripts__sync_commands.py", "source_location": "L17", "weight": 1.0}, {"source": "fixes_scripts_sync_commands_py", "target": "scripts_sync_commands_main", "relation": "contains", "confidence": "EXTRACTED", "source_file": "fixes/scripts__sync_commands.py", "source_location": "L22", "weight": 1.0}, {"source": "scripts_sync_commands_rationale_1", "target": "fixes_scripts_sync_commands_py", "relation": "rationale_for", "confidence": "EXTRACTED", "source_file": "fixes/scripts__sync_commands.py", "source_location": "L1", "weight": 1.0}], "raw_calls": [{"caller_nid": "scripts_sync_commands_main", "callee": "Bot", "source_file": "fixes/scripts__sync_commands.py", "source_location": "L23"}, {"caller_nid": "scripts_sync_commands_main", "callee": "login", "source_file": "fixes/scripts__sync_commands.py", "source_location": "L26"}, {"caller_nid": "scripts_sync_commands_main", "callee": "load_extension", "source_file": "fixes/scripts__sync_commands.py", "source_location": "L30"}, {"caller_nid": "scripts_sync_commands_main", "callee": "print", "source_file": "fixes/scripts__sync_commands.py", "source_location": "L31"}, {"caller_nid": "scripts_sync_commands_main", "callee": "print", "source_file": "fixes/scripts__sync_commands.py", "source_location": "L33"}, {"caller_nid": "scripts_sync_commands_main", "callee": "Object", "source_file": "fixes/scripts__sync_commands.py", "source_location": "L36"}, {"caller_nid": "scripts_sync_commands_main", "callee": "int", "source_file": "fixes/scripts__sync_commands.py", "source_location": "L36"}, {"caller_nid": "scripts_sync_commands_main", "callee": "copy_global_to", "source_file": "fixes/scripts__sync_commands.py", "source_location": "L37"}, {"caller_nid": "scripts_sync_commands_main", "callee": "sync", "source_file": "fixes/scripts__sync_commands.py", "source_location": "L38"}, {"caller_nid": "scripts_sync_commands_main", "callee": "print", "source_file": "fixes/scripts__sync_commands.py", "source_location": "L39"}, {"caller_nid": "scripts_sync_commands_main", "callee": "len", "source_file": "fixes/scripts__sync_commands.py", "source_location": "L39"}, {"caller_nid": "scripts_sync_commands_main", "callee": "sync", "source_file": "fixes/scripts__sync_commands.py", "source_location": "L41"}, {"caller_nid": "scripts_sync_commands_main", "callee": "print", "source_file": "fixes/scripts__sync_commands.py", "source_location": "L42"}, {"caller_nid": "scripts_sync_commands_main", "callee": "len", "source_file": "fixes/scripts__sync_commands.py", "source_location": "L42"}, {"caller_nid": "scripts_sync_commands_main", "callee": "print", "source_file": "fixes/scripts__sync_commands.py", "source_location": "L44"}]}